[{"id":59048135,"rarity":"Super Rare","code":"WSUP-EN005","price":"0.06"},{"id":35537251,"rarity":"Super Rare","code":"WSUP-EN013","price":"0.15"},{"id":61156777,"rarity":"Super Rare","code":"WSUP-EN048","price":"0.16"},{"id":24861088,"rarity":"Prismatic Secret Rare","code":"WSUP-EN001","price":"0.19"},{"id":73866096,"rarity":"Super Rare","code":"WSUP-EN008","price":"0.24"},{"id":34898052,"rarity":"Super Rare","code":"WSUP-EN038","price":"0.27"},{"id":54407825,"rarity":"Prismatic Secret Rare","code":"WSUP-EN042","price":"0.35"},{"id":63060238,"rarity":"Prismatic Secret Rare","code":"WSUP-EN032","price":"0.52"},{"id":45010690,"rarity":"Super Rare","code":"WSUP-EN036","price":"0.20"},{"id":28884172,"rarity":"Super Rare","code":"WSUP-EN028","price":"0.26"},{"id":91499077,"rarity":"Super Rare","code":"WSUP-EN027","price":"0.17"},{"id":387282,"rarity":"Prismatic Secret Rare","code":"WSUP-EN006","price":"0.97"},{"id":46659709,"rarity":"Prismatic Secret Rare","code":"WSUP-EN010","price":"0.46"},{"id":9260791,"rarity":"Super Rare","code":"WSUP-EN009","price":"0.83"},{"id":53334641,"rarity":"Super Rare","code":"WSUP-EN035","price":"0.12"},{"id":80802524,"rarity":"Super Rare","code":"WSUP-EN043","price":"0.12"},{"id":64283880,"rarity":"Super Rare","code":"WSUP-EN029","price":"0.13"},{"id":54629413,"rarity":"Super Rare","code":"WSUP-EN040","price":"0.13"},{"id":34761062,"rarity":"Super Rare","code":"WSUP-EN047","price":"0.09"},{"id":87255382,"rarity":"Super Rare","code":"WSUP-EN003","price":"0.10"},{"id":65848811,"rarity":"Super Rare","code":"WSUP-EN016","price":"0.40"},{"id":1833916,"rarity":"Super Rare","code":"WSUP-EN017","price":"0.10"},{"id":91677585,"rarity":"Prismatic Secret Rare","code":"WSUP-EN030","price":"0.20"},{"id":90098780,"rarity":"Super Rare","code":"WSUP-EN023","price":"0.28"},{"id":71415349,"rarity":"Super Rare","code":"WSUP-EN037","price":"0.13"},{"id":8316565,"rarity":"Super Rare","code":"WSUP-EN015","price":"0.15"},{"id":7541475,"rarity":"Super Rare","code":"WSUP-EN049","price":"0.27"},{"id":63881033,"rarity":"Prismatic Secret Rare","code":"WSUP-EN025","price":"0.17"},{"id":26949946,"rarity":"Super Rare","code":"WSUP-EN034","price":"0.09"},{"id":90555947,"rarity":"Super Rare","code":"WSUP-EN033","price":"0.30"},{"id":23649496,"rarity":"Super Rare","code":"WSUP-EN004","price":"0.10"},{"id":50260683,"rarity":"Super Rare","code":"WSUP-EN002","price":"0.35"},{"id":46871387,"rarity":"Super Rare","code":"WSUP-EN007","price":"1.08"},{"id":71921856,"rarity":"Super Rare","code":"WSUP-EN014","price":"0.17"},{"id":63504681,"rarity":"Prismatic Secret Rare","code":"WSUP-EN022","price":"0.42"},{"id":65305468,"rarity":"Prismatic Secret Rare","code":"WSUP-EN026","price":"0.19"},{"id":37115973,"rarity":"Prismatic Secret Rare","code":"WSUP-EN021","price":"0.27"},{"id":26493435,"rarity":"Prismatic Secret Rare","code":"WSUP-EN024","price":"0.05"},{"id":13760677,"rarity":"Super Rare","code":"WSUP-EN044","price":"0.08"},{"id":60434189,"rarity":"Prismatic Secret Rare","code":"WSUP-EN050","price":"0.10"},{"id":72044448,"rarity":"Super Rare","code":"WSUP-EN011","price":"0.39"},{"id":10282757,"rarity":"Super Rare","code":"WSUP-EN039","price":"0.08"},{"id":50155385,"rarity":"Super Rare","code":"WSUP-EN045","price":"0.12"},{"id":64726269,"rarity":"Super Rare","code":"WSUP-EN019","price":"0.16"},{"id":38331564,"rarity":"Prismatic Secret Rare","code":"WSUP-EN018","price":"0.06"},{"id":91110378,"rarity":"Prismatic Secret Rare","code":"WSUP-EN020","price":"0.07"},{"id":8038143,"rarity":"Prismatic Secret Rare","code":"WSUP-EN012","price":"0.17"},{"id":27062594,"rarity":"Prismatic Secret Rare","code":"WSUP-EN031","price":"0.16"},{"id":81028112,"rarity":"Super Rare","code":"WSUP-EN041","price":"0.24"},{"id":86559484,"rarity":"Super Rare","code":"WSUP-EN046","price":"0.16"}]