[{"id":21044178,"rarity":"Super Rare","code":"THSF-EN047","price":"0.10"},{"id":46052429,"rarity":"Super Rare","code":"THSF-EN052","price":"0.27"},{"id":27632240,"rarity":"Super Rare","code":"THSF-EN046","price":"0.05"},{"id":78910579,"rarity":"Super Rare","code":"THSF-EN060","price":"0.11"},{"id":28985331,"rarity":"Super Rare","code":"THSF-EN035","price":"0.24"},{"id":88301833,"rarity":"Super Rare","code":"THSF-EN054","price":"0.11"},{"id":48976825,"rarity":"Super Rare","code":"THSF-EN051","price":"0.27"},{"id":45812361,"rarity":"Super Rare","code":"THSF-EN044","price":"0.11"},{"id":15854426,"rarity":"Super Rare","code":"THSF-EN056","price":"0.11"},{"id":77153811,"rarity":"Super Rare","code":"THSF-EN038","price":"0.14"},{"id":30492798,"rarity":"Super Rare","code":"THSF-EN040","price":"0.12"},{"id":34358408,"rarity":"Super Rare","code":"THSF-EN037","price":"0.18"},{"id":4141820,"rarity":"Super Rare","code":"THSF-EN039","price":"0.09"},{"id":8903700,"rarity":"Super Rare","code":"THSF-EN036","price":"0.44"},{"id":53180020,"rarity":"Super Rare","code":"THSF-EN012","price":"0.33"},{"id":57103969,"rarity":"Super Rare","code":"THSF-EN057","price":"0.08"},{"id":66399675,"rarity":"Super Rare","code":"THSF-EN041","price":"0.09"},{"id":63942761,"rarity":"Super Rare","code":"THSF-EN043","price":"0.13"},{"id":29888389,"rarity":"Super Rare","code":"THSF-EN042","price":"0.27"},{"id":47106439,"rarity":"Super Rare","code":"THSF-EN045","price":"0.13"},{"id":27796375,"rarity":"Super Rare","code":"THSF-EN011","price":"0.32"},{"id":95492061,"rarity":"Super Rare","code":"THSF-EN033","price":"0.20"},{"id":93368494,"rarity":"Secret Rare","code":"THSF-EN001","price":"0.38"},{"id":4906301,"rarity":"Super Rare","code":"THSF-EN034","price":"0.32"},{"id":51124303,"rarity":"Secret Rare","code":"THSF-EN021","price":"0.09"},{"id":14735698,"rarity":"Secret Rare","code":"THSF-EN020","price":"0.07"},{"id":26674724,"rarity":"Secret Rare","code":"THSF-EN014","price":"1.77"},{"id":52846880,"rarity":"Secret Rare","code":"THSF-EN018","price":"1.06"},{"id":99185129,"rarity":"Secret Rare","code":"THSF-EN013","price":"0.07"},{"id":88240999,"rarity":"Secret Rare","code":"THSF-EN019","price":"0.11"},{"id":52068432,"rarity":"Secret Rare","code":"THSF-EN015","price":"0.28"},{"id":89463537,"rarity":"Secret Rare","code":"THSF-EN016","price":"0.43"},{"id":25857246,"rarity":"Secret Rare","code":"THSF-EN017","price":"0.48"},{"id":96729612,"rarity":"Super Rare","code":"THSF-EN053","price":"0.22"},{"id":11556339,"rarity":"Super Rare","code":"THSF-EN032","price":"0.49"},{"id":14513016,"rarity":"Secret Rare","code":"THSF-EN023","price":"0.10"},{"id":87118301,"rarity":"Secret Rare","code":"THSF-EN022","price":"0.96"},{"id":40907115,"rarity":"Secret Rare","code":"THSF-EN024","price":"0.55"},{"id":86274272,"rarity":"Secret Rare","code":"THSF-EN028","price":"1.04"},{"id":48063985,"rarity":"Secret Rare","code":"THSF-EN030","price":"0.12"},{"id":12678870,"rarity":"Secret Rare","code":"THSF-EN029","price":"0.37"},{"id":75457624,"rarity":"Super Rare","code":"THSF-EN031","price":"0.23"},{"id":25796442,"rarity":"Super Rare","code":"THSF-EN055","price":"0.14"},{"id":54351224,"rarity":"Super Rare","code":"THSF-EN050","price":"0.11"},{"id":51452091,"rarity":"Super Rare","code":"THSF-EN058","price":"0.45"},{"id":90307777,"rarity":"Super Rare","code":"THSF-EN010","price":"0.30"},{"id":68073522,"rarity":"Super Rare","code":"THSF-EN049","price":"0.18"},{"id":5758500,"rarity":"Super Rare","code":"THSF-EN048","price":"0.15"},{"id":86396750,"rarity":"Super Rare","code":"THSF-EN025","price":"0.44"},{"id":49885567,"rarity":"Super Rare","code":"THSF-EN027","price":"0.70"},{"id":13890468,"rarity":"Super Rare","code":"THSF-EN026","price":"0.25"},{"id":5851097,"rarity":"Super Rare","code":"THSF-EN059","price":"0.91"},{"id":27918963,"rarity":"Super Rare","code":"THSF-EN008","price":"0.12"},{"id":65247798,"rarity":"Secret Rare","code":"THSF-EN003","price":"0.20"},{"id":92246806,"rarity":"Secret Rare","code":"THSF-EN004","price":"0.20"},{"id":28630501,"rarity":"Secret Rare","code":"THSF-EN005","price":"0.18"},{"id":39853199,"rarity":"Secret Rare","code":"THSF-EN002","price":"0.25"},{"id":65025250,"rarity":"Super Rare","code":"THSF-EN006","price":"0.12"},{"id":91420254,"rarity":"Super Rare","code":"THSF-EN007","price":"0.11"},{"id":54903668,"rarity":"Super Rare","code":"THSF-EN009","price":"0.11"}]